accounting_sh/__init__.py
accounting_sh/accounting.py
accounting_sh/exceptions.py
accounting_sh/api/__init__.py
accounting_sh/api/account_connections_api.py
accounting_sh/api/accounting_codes_api.py
accounting_sh/api/accounts_api.py
accounting_sh/api/attachments_api.py
accounting_sh/api/auth_api.py
accounting_sh/api/bills_api.py
accounting_sh/api/categories_api.py
accounting_sh/api/companies_api.py
accounting_sh/api/company_statistics_api.py
accounting_sh/api/contacts_api.py
accounting_sh/api/countries_api.py
accounting_sh/api/credentials_api.py
accounting_sh/api/currency_api.py
accounting_sh/api/documents_api.py
accounting_sh/api/expense_reports_api.py
accounting_sh/api/export_api.py
accounting_sh/api/invoices_api.py
accounting_sh/api/logs_api.py
accounting_sh/api/notification_api.py
accounting_sh/api/notification_types_api.py
accounting_sh/api/o_auth_config_api.py
accounting_sh/api/payments_api.py
accounting_sh/api/quotes_api.py
accounting_sh/api/receipts_api.py
accounting_sh/api/revenues_api.py
accounting_sh/api/rossum_api.py
accounting_sh/api/search_api.py
accounting_sh/api/settings_api.py
accounting_sh/api/statistics_api.py
accounting_sh/api/tags_api.py
accounting_sh/api/tax_api.py
accounting_sh/api/transactions_api.py
accounting_sh/api/transfers_api.py
accounting_sh/api/users_api.py
accounting_sh/api/vatid_api.py
accounting_sh/api/webhooks_api.py
accounting_sh-1.3.5.dist-info/licenses/LICENSE
accounting_sh-1.3.5.dist-info/METADATA
accounting_sh-1.3.5.dist-info/WHEEL
accounting_sh-1.3.5.dist-info/top_level.txt
accounting_sh-1.3.5.dist-info/RECORD
