Metadata-Version: 2.4
Name: accounting_sh
Version: 1.3.5
Summary: Accounting API
Home-page: 
Author: STAN-TAB CORP. LTD
Author-email: "STAN-TAB CORP. LTD" <support@stantabcorp.com>
License:                                  Apache License
Project-URL: Homepage, https://accounting.sh
Project-URL: Repository, https://github.com/accounting-sh/python_sdk.git
Project-URL: Issues, https://github.com/accounting-sh/python_sdk/issues
Keywords: OpenAPI,Accounting API
Classifier: Development Status :: 3 - Alpha
Classifier: Intended Audience :: Developers
Classifier: Intended Audience :: Information Technology
Classifier: Intended Audience :: Financial and Insurance Industry
Classifier: License :: OSI Approved :: Apache Software License
Classifier: Topic :: Office/Business
Classifier: Topic :: Office/Business :: Financial
Classifier: Topic :: Office/Business :: Financial :: Accounting
Classifier: Programming Language :: Python
Classifier: Programming Language :: Python :: 3
Classifier: Programming Language :: Python :: 3.10
Classifier: Programming Language :: Python :: 3.11
Classifier: Programming Language :: Python :: 3.12
Requires-Python: >=3.10
License-File: LICENSE
Requires-Dist: requests>=2.32.2
Requires-Dist: typing-extensions>=4.7.1
Dynamic: author
Dynamic: license-file
